{
  "lint": {
    "rules": [
      "polymer-3"
    ]
  },
  "builds": [{
    "name":"default",
    "addServiceWorker": true,
    "swPrecacheConfig": "sw-precache-config.js",
    "html": {
      "minify": true
    },
    "css": {
      "minify": true
    },
    "js": {
      "minify": true,
      "compile":true,
      "transformModulesToAmd": true
    }
  }],
  "entrypoint": "index.html",
  "shell": "src/danipani.js",
  "extraDependencies": [
    "manifest.json",
    "node_modules/@webcomponents/webcomponentsjs/**",
    "robots.txt",
    "sitemap.xml"
  ]
}